pyasjp/__init__.py
pyasjp/__main__.py
pyasjp/api.py
pyasjp/meanings.py
pyasjp/models.py
pyasjp/commands/__init__.py
pyasjp/commands/diff.py
pyasjp/commands/formatted.py
pyasjp-1.4.0.dist-info/licenses/LICENSE
pyasjp-1.4.0.dist-info/METADATA
pyasjp-1.4.0.dist-info/WHEEL
pyasjp-1.4.0.dist-info/entry_points.txt
pyasjp-1.4.0.dist-info/top_level.txt
pyasjp-1.4.0.dist-info/RECORD
